sim/tb/axil/axil_test.sv
//*****************************************************************************
// Copyright (C) 2025 WanderingKitsune. All rights reserved.
// SPDX-License-Identifier: MIT
// 
// File:        axil_test.sv
// Description: AXI4-Lite Test Module
// Repository:  https://github.com/WanderingKitsune/axi_lib.git
// 
// Modification History:
// Ver   Who       Date        Changes
// ----  ----  ----------  ----------------------------------------------------
// 1.0         2025/12/25  Initial release
//*****************************************************************************

`timescale 1ns / 1ps

module axil_test
#(
    parameter DATA_WIDTH = 32,
    parameter ADDR_WIDTH = 16,
    parameter STRB_WIDTH = (DATA_WIDTH/8)
)
(
    input  wire                   clk,
    input  wire                   rst,

    input  wire [ADDR_WIDTH-1:0]  s_axil_awaddr,
    input  wire [2:0]             s_axil_awprot,
    input  wire                   s_axil_awvalid,
    output wire                   s_axil_awready,
    input  wire [DATA_WIDTH-1:0]  s_axil_wdata,
    input  wire [STRB_WIDTH-1:0]  s_axil_wstrb,
    input  wire                   s_axil_wvalid,
    output wire                   s_axil_wready,
    output wire [1:0]             s_axil_bresp,
    output wire                   s_axil_bvalid,
    input  wire                   s_axil_bready,
    input  wire [ADDR_WIDTH-1:0]  s_axil_araddr,
    input  wire [2:0]             s_axil_arprot,
    input  wire                   s_axil_arvalid,
    output wire                   s_axil_arready,
    output wire [DATA_WIDTH-1:0]  s_axil_rdata,
    output wire [1:0]             s_axil_rresp,
    output wire                   s_axil_rvalid,
    input  wire                   s_axil_rready,

    output wire [ADDR_WIDTH-1:0]  m_axil_awaddr,
    output wire [2:0]             m_axil_awprot,
    output wire                   m_axil_awvalid,
    input  wire                   m_axil_awready,
    output wire [DATA_WIDTH-1:0]  m_axil_wdata,
    output wire [STRB_WIDTH-1:0]  m_axil_wstrb,
    output wire                   m_axil_wvalid,
    input  wire                   m_axil_wready,
    input  wire [1:0]             m_axil_bresp,
    input  wire                   m_axil_bvalid,
    output wire                   m_axil_bready,
    output wire [ADDR_WIDTH-1:0]  m_axil_araddr,
    output wire [2:0]             m_axil_arprot,
    output wire                   m_axil_arvalid,
    input  wire                   m_axil_arready,
    input  wire [DATA_WIDTH-1:0]  m_axil_rdata,
    input  wire [1:0]             m_axil_rresp,
    input  wire                   m_axil_rvalid,
    output wire                   m_axil_rready
);

assign m_axil_awaddr  = s_axil_awaddr;
assign m_axil_awprot  = s_axil_awprot;
assign m_axil_awvalid = s_axil_awvalid;
assign s_axil_awready = m_axil_awready;

assign m_axil_wdata   = s_axil_wdata;
assign m_axil_wstrb   = s_axil_wstrb;
assign m_axil_wvalid  = s_axil_wvalid;
assign s_axil_wready  = m_axil_wready;

assign s_axil_bresp   = m_axil_bresp;
assign s_axil_bvalid  = m_axil_bvalid;
assign m_axil_bready  = s_axil_bready;

assign m_axil_araddr  = s_axil_araddr;
assign m_axil_arprot  = s_axil_arprot;
assign m_axil_arvalid = s_axil_arvalid;
assign s_axil_arready = m_axil_arready;

assign s_axil_rdata   = m_axil_rdata;
assign s_axil_rresp   = m_axil_rresp;
assign s_axil_rvalid  = m_axil_rvalid;
assign m_axil_rready  = s_axil_rready;

endmodule

sim/tb/axil/waveform.vcd
$version Generated by VerilatedVcd $end
$timescale 1ps $end
 $scope module TOP $end
  $var wire 1 # clk $end
  $var wire 1 $ rst $end
  $var wire 16 % s_axil_awaddr [15:0] $end
  $var wire 3 & s_axil_awprot [2:0] $end
  $var wire 1 ' s_axil_awvalid $end
  $var wire 1 ( s_axil_awready $end
  $var wire 32 ) s_axil_wdata [31:0] $end
  $var wire 4 * s_axil_wstrb [3:0] $end
  $var wire 1 + s_axil_wvalid $end
  $var wire 1 , s_axil_wready $end
  $var wire 2 - s_axil_bresp [1:0] $end
  $var wire 1 . s_axil_bvalid $end
  $var wire 1 / s_axil_bready $end
  $var wire 16 0 s_axil_araddr [15:0] $end
  $var wire 3 1 s_axil_arprot [2:0] $end
  $var wire 1 2 s_axil_arvalid $end
  $var wire 1 3 s_axil_arready $end
  $var wire 32 4 s_axil_rdata [31:0] $end
  $var wire 2 5 s_axil_rresp [1:0] $end
  $var wire 1 6 s_axil_rvalid $end
  $var wire 1 7 s_axil_rready $end
  $var wire 16 8 m_axil_awaddr [15:0] $end
  $var wire 3 9 m_axil_awprot [2:0] $end
  $var wire 1 : m_axil_awvalid $end
  $var wire 1 ; m_axil_awready $end
  $var wire 32 < m_axil_wdata [31:0] $end
  $var wire 4 = m_axil_wstrb [3:0] $end
  $var wire 1 > m_axil_wvalid $end
  $var wire 1 ? m_axil_wready $end
  $var wire 2 @ m_axil_bresp [1:0] $end
  $var wire 1 A m_axil_bvalid $end
  $var wire 1 B m_axil_bready $end
  $var wire 16 C m_axil_araddr [15:0] $end
  $var wire 3 D m_axil_arprot [2:0] $end
  $var wire 1 E m_axil_arvalid $end
  $var wire 1 F m_axil_arready $end
  $var wire 32 G m_axil_rdata [31:0] $end
  $var wire 2 H m_axil_rresp [1:0] $end
  $var wire 1 I m_axil_rvalid $end
  $var wire 1 J m_axil_rready $end
  $scope module axil_test $end
   $var wire 1 K clk $end
   $var wire 1 L rst $end
   $var wire 16 M s_axil_awaddr [15:0] $end
   $var wire 3 N s_axil_awprot [2:0] $end
   $var wire 1 O s_axil_awvalid $end
   $var wire 1 P s_axil_awready $end
   $var wire 32 Q s_axil_wdata [31:0] $end
   $var wire 4 R s_axil_wstrb [3:0] $end
   $var wire 1 S s_axil_wvalid $end
   $var wire 1 T s_axil_wready $end
   $var wire 2 U s_axil_bresp [1:0] $end
   $var wire 1 V s_axil_bvalid $end
   $var wire 1 W s_axil_bready $end
   $var wire 16 X s_axil_araddr [15:0] $end
   $var wire 3 Y s_axil_arprot [2:0] $end
   $var wire 1 Z s_axil_arvalid $end
   $var wire 1 [ s_axil_arready $end
   $var wire 32 \ s_axil_rdata [31:0] $end
   $var wire 2 ] s_axil_rresp [1:0] $end
   $var wire 1 ^ s_axil_rvalid $end
   $var wire 1 _ s_axil_rready $end
   $var wire 16 ` m_axil_awaddr [15:0] $end
   $var wire 3 a m_axil_awprot [2:0] $end
   $var wire 1 b m_axil_awvalid $end
   $var wire 1 c m_axil_awready $end
   $var wire 32 d m_axil_wdata [31:0] $end
   $var wire 4 e m_axil_wstrb [3:0] $end
   $var wire 1 f m_axil_wvalid $end
   $var wire 1 g m_axil_wready $end
   $var wire 2 h m_axil_bresp [1:0] $end
   $var wire 1 i m_axil_bvalid $end
   $var wire 1 j m_axil_bready $end
   $var wire 16 k m_axil_araddr [15:0] $end
   $var wire 3 l m_axil_arprot [2:0] $end
   $var wire 1 m m_axil_arvalid $end
   $var wire 1 n m_axil_arready $end
   $var wire 32 o m_axil_rdata [31:0] $end
   $var wire 2 p m_axil_rresp [1:0] $end
   $var wire 1 q m_axil_rvalid $end
   $var wire 1 r m_axil_rready $end
  $upscope $end
 $upscope $end
$enddefinitions $end


#1
1#
1$
b0000000000000000 %
b000 &
0'
1(
b00000000000000000000000000000000 )
b0000 *
0+
1,
b00 -
0.
0/
b0000000000000000 0
b000 1
02
13
b00000000000000000000000000000000 4
b00 5
06
07
b0000000000000000 8
b000 9
0:
1;
b00000000000000000000000000000000 <
b0000 =
0>
1?
b00 @
0A
0B
b0000000000000000 C
b000 D
0E
1F
b00000000000000000000000000000000 G
b00 H
0I
0J
1K
1L
b0000000000000000 M
b000 N
0O
1P
b00000000000000000000000000000000 Q
b0000 R
0S
1T
b00 U
0V
0W
b0000000000000000 X
b000 Y
0Z
1[
b00000000000000000000000000000000 \
b00 ]
0^
0_
b0000000000000000 `
b000 a
0b
1c
b00000000000000000000000000000000 d
b0000 e
0f
1g
b00 h
0i
0j
b0000000000000000 k
b000 l
0m
1n
b00000000000000000000000000000000 o
b00 p
0q
0r
#2
0#
0K
#3
1#
1K
#4
0#
0K
#5
1#
1K
#6
0#
0K
#7
1#
1K
#8
0#
0K
#9
1#
1K
#10
0#
0$
0K
0L
#11
1#
1K
#12
0#
0K
#13
1#
1K
#14
0#
0K
#15
1#
1K
#16
0#
0K
#17
1#
1K
#18
0#
0K
#19
1#
1K
#20
0#
0K
#21
1#
b0000000100000000 %
1'
b10101011110011010001001000110100 )
b1111 *
1+
b0000000100000000 8
1:
b10101011110011010001001000110100 <
b1111 =
1>
1K
b0000000100000000 M
1O
b10101011110011010001001000110100 Q
b1111 R
1S
b0000000100000000 `
1b
b10101011110011010001001000110100 d
b1111 e
1f
#22
0#
0K
#23
1#
0(
0,
1.
0;
0?
1A
1K
0P
0T
1V
0c
0g
1i
#24
0#
0K
#25
1#
b0000000000000000 %
0'
b00000000000000000000000000000000 )
b0000 *
0+
1/
b0000000000000000 8
0:
b00000000000000000000000000000000 <
b0000 =
0>
1B
1K
b0000000000000000 M
0O
b00000000000000000000000000000000 Q
b0000 R
0S
1W
b0000000000000000 `
0b
b00000000000000000000000000000000 d
b0000 e
0f
1j
#26
0#
0K
#27
1#
b0000001000000000 %
1'
1(
b00010010000100100001001000010010 )
b1111 *
1+
1,
0.
0/
b0000001000000000 8
1:
1;
b00010010000100100001001000010010 <
b1111 =
1>
1?
0A
0B
1K
b0000001000000000 M
1O
1P
b00010010000100100001001000010010 Q
b1111 R
1S
1T
0V
0W
b0000001000000000 `
1b
1c
b00010010000100100001001000010010 d
b1111 e
1f
1g
0i
0j
#28
0#
0K
#29
1#
0(
0,
1.
0;
0?
1A
1K
0P
0T
1V
0c
0g
1i
#30
0#
0K
#31
1#
b0000000000000000 %
0'
b00000000000000000000000000000000 )
b0000 *
0+
1/
b0000000000000000 8
0:
b00000000000000000000000000000000 <
b0000 =
0>
1B
1K
b0000000000000000 M
0O
b00000000000000000000000000000000 Q
b0000 R
0S
1W
b0000000000000000 `
0b
b00000000000000000000000000000000 d
b0000 e
0f
1j
#32
0#
0K
#33
1#
b0000001100000000 %
1'
1(
b00010000000000000000000000000000 )
b1111 *
1+
1,
0.
0/
b0000001100000000 8
1:
1;
b00010000000000000000000000000000 <
b1111 =
1>
1?
0A
0B
1K
b0000001100000000 M
1O
1P
b00010000000000000000000000000000 Q
b1111 R
1S
1T
0V
0W
b0000001100000000 `
1b
1c
b00010000000000000000000000000000 d
b1111 e
1f
1g
0i
0j
#34
0#
0K
#35
1#
0(
0,
1.
0;
0?
1A
1K
0P
0T
1V
0c
0g
1i
#36
0#
0K
#37
1#
b0000000000000000 %
0'
b00000000000000000000000000000000 )
b0000 *
0+
1/
b0000000000000000 8
0:
b00000000000000000000000000000000 <
b0000 =
0>
1B
1K
b0000000000000000 M
0O
b00000000000000000000000000000000 Q
b0000 R
0S
1W
b0000000000000000 `
0b
b00000000000000000000000000000000 d
b0000 e
0f
1j
#38
0#
0K
#39
1#
1(
1,
0.
0/
1;
1?
0A
0B
1K
1P
1T
0V
0W
1c
1g
0i
0j
